a2a/__init__.py
a2a/client/__init__.py
a2a/client/card_resolver.py
a2a/client/client.py
a2a/server/__init__.py
a2a/server/server.py
a2a/server/task_manager.py
a2a/server/utils.py
a2a/types.py
a2a/utils/in_memory_cache.py
a2a/utils/push_notification_auth.py
pya2a-0.1.1.dist-info/LICENSE
pya2a-0.1.1.dist-info/METADATA
pya2a-0.1.1.dist-info/WHEEL
pya2a-0.1.1.dist-info/RECORD
