Metadata-Version: 2.1
Name: pya2a
Version: 0.1.1
Summary: A2A SDK - Agent to Agent Protocol Python SDK
Home-page: https://github.com/jeff_kit/a2a
Author: jeff_kit
Author-email: bbmyth@gmail.com
Requires-Python: >=3.8,<3.14
Classifier: Intended Audience :: Developers
Classifier: License :: OSI Approved :: MIT License
Classifier: Operating System :: OS Independent
Classifier: Programming Language :: Python :: 3
Classifier: Programming Language :: Python :: 3.8
Classifier: Programming Language :: Python :: 3.9
Classifier: Programming Language :: Python :: 3.10
Classifier: Programming Language :: Python :: 3.11
Classifier: Programming Language :: Python :: 3.12
Classifier: Programming Language :: Python :: 3.13
Classifier: Topic :: Software Development :: Libraries :: Python Modules
Provides-Extra: server
Requires-Dist: cryptography (>=40.0.0,<42.0.0)
Requires-Dist: httpx (>=0.23.0,<1.0.0)
Requires-Dist: httpx-sse (>=0.3.1,<1.0.0)
Requires-Dist: jwcrypto (>=1.4.2,<2.0.0)
Requires-Dist: pydantic (>=2.0.0,<3.0.0)
Requires-Dist: pyjwt (>=2.6.0,<3.0.0)
Requires-Dist: sse_starlette (>=2.0.0) ; extra == "server"
Requires-Dist: starlette (>=0.27.0,<1.0.0) ; extra == "server"
Requires-Dist: typing-extensions (>=4.5.0,<5.0.0)
Project-URL: Documentation, https://github.com/jeff_kit/a2a#readme
Project-URL: Repository, https://github.com/jeff_kit/a2a
